{
	"id": "47827",
	"quantity": 240,
	"attributes": [
		{
			"name": "Højde",
			"type": 3,
			"units": "mm",
			"value": "300.00",
			"id": 3
		},
		{
			"name": "Bredde",
			"type": 3,
			"units": "mm",
			"value": "390.00",
			"id": 4
		},
		{ "name": "Dybde", "type": 3, "units": "mm", "value": "47", "id": 49 },
		{
			"name": "ISO 16890",
			"type": 0,
			"units": null,
			"value": "ISO ePM10 50%",
			"id": 51
		},
		{
			"name": "Webshop",
			"type": 0,
			"units": null,
			"value": "Ja",
			"id": 70
		},
		{
			"name": "Paneltype",
			"type": 0,
			"units": null,
			"value": "Z-line",
			"id": 104
		},
		{
			"name": "Ramme (panelfilter)",
			"type": 0,
			"units": null,
			"value": "Fiber",
			"id": 109
		}
	],
	"qaReportId": 1,
	"controlPoints": [
		{
			"id": 1,
			"frequencyId": 1,
			"image": "https://syria.liveuamap.com/pics/2022/04/23/22430986_0.jpg",
			"type": 3,
			"lowerTolerance": null,
			"upperTolerance": null,
			"attributes": [{ "id": 3, "maxValue": null, "minValue": null }],
			"descriptions": "",
			"description": "This is a description",
			"frequency": [
				{
					"id": 1,
					"to25": 23,
					"to50": 2,
					"to100": 343,
					"to200": 5,
					"to300": 5,
					"to500": 6,
					"to700": 66,
					"to1000": 7,
					"to1500": 5,
					"to2000": 76,
					"to3000": 76,
					"to4000": 766,
					"to5000": 69
				}
			],
			"controlPointType": 1,
			"expectedValue": "300.00",
			"units": "mm",
			"toleranceText": "",
			"answer": ""
		},
		{
			"id": 2,
			"frequencyId": 1,
			"image": "https://syria.liveuamap.com/pics/2022/04/23/22430986_0.jpg",
			"type": 3,
			"lowerTolerance": 1,
			"upperTolerance": 1,
			"attributes": [{ "id": 4, "maxValue": 400, "minValue": 300 }],
			"descriptions": "",
			"description": "This is a description",
			"frequency": [
				{
					"id": 1,
					"to25": 23,
					"to50": 2,
					"to100": 343,
					"to200": 5,
					"to300": 5,
					"to500": 6,
					"to700": 66,
					"to1000": 7,
					"to1500": 5,
					"to2000": 76,
					"to3000": 76,
					"to4000": 766,
					"to5000": 69
				}
			],
			"controlPointType": 1,
			"expectedValue": "390.00",
			"units": "mm",
			"toleranceText": "+/-1mm",
			"answer": ""
		},
		{
			"id": 3,
			"frequencyId": 1,
			"image": "https://syria.liveuamap.com/pics/2022/04/23/22430986_0.jpg",
			"type": 3,
			"lowerTolerance": 1,
			"upperTolerance": 6,
			"attributes": [{ "id": 49, "maxValue": 50, "minValue": 30 }],
			"descriptions": "",
			"description": "This is a description",
			"frequency": [
				{
					"id": 1,
					"to25": 23,
					"to50": 2,
					"to100": 343,
					"to200": 5,
					"to300": 5,
					"to500": 6,
					"to700": 66,
					"to1000": 7,
					"to1500": 5,
					"to2000": 76,
					"to3000": 76,
					"to4000": 766,
					"to5000": 69
				}
			],
			"controlPointType": 1,
			"expectedValue": "47",
			"units": "mm",
			"toleranceText": "+6/-1mm",
			"answer": ""
		},
		{
			"id": 4,
			"frequencyId": 1,
			"image": "https://syria.liveuamap.com/pics/2022/04/23/22430986_0.jpg",
			"type": 1,
			"lowerTolerance": null,
			"upperTolerance": null,
			"attributes": [{ "id": 51, "maxValue": null, "minValue": null }],
			"descriptions": "",
			"description": "This is a description",
			"frequency": [
				{
					"id": 1,
					"to25": 23,
					"to50": 2,
					"to100": 343,
					"to200": 5,
					"to300": 5,
					"to500": 6,
					"to700": 66,
					"to1000": 7,
					"to1500": 5,
					"to2000": 76,
					"to3000": 76,
					"to4000": 766,
					"to5000": 69
				}
			],
			"controlPointType": 1,
			"expectedValue": "ISO ePM10 50%",
			"units": "Text",
			"toleranceText": "",
			"answer": ""
		},
		{
			"id": 5,
			"frequencyId": 1,
			"image": "https://syria.liveuamap.com/pics/2022/04/23/22430986_0.jpg",
			"type": 0,
			"lowerTolerance": null,
			"upperTolerance": null,
			"attributes": [{ "id": 70, "maxValue": null, "minValue": null }],
			"descriptions": "",
			"description": "This is a description",
			"frequency": [
				{
					"id": 1,
					"to25": 23,
					"to50": 2,
					"to100": 343,
					"to200": 5,
					"to300": 5,
					"to500": 6,
					"to700": 66,
					"to1000": 7,
					"to1500": 5,
					"to2000": 76,
					"to3000": 76,
					"to4000": 766,
					"to5000": 69
				}
			],
			"options": [
				{ "id": 1, "controlPointId": 5, "value": "Yes" },
				{ "id": 2, "controlPointId": 5, "value": "No" }
			],
			"controlPointType": 1,
			"expectedValue": "Ja",
			"units": "Yes/No",
			"toleranceText": "",
			"answer": ""
		},
		{
			"id": 6,
			"frequencyId": 1,
			"image": "https://syria.liveuamap.com/pics/2022/04/23/22430986_0.jpg",
			"type": 0,
			"lowerTolerance": null,
			"upperTolerance": null,
			"attributes": [{ "id": 104, "maxValue": null, "minValue": null }],
			"descriptions": "",
			"description": "This is a description",
			"frequency": [
				{
					"id": 1,
					"to25": 23,
					"to50": 2,
					"to100": 343,
					"to200": 5,
					"to300": 5,
					"to500": 6,
					"to700": 66,
					"to1000": 7,
					"to1500": 5,
					"to2000": 76,
					"to3000": 76,
					"to4000": 766,
					"to5000": 69
				}
			],
			"options": [
				{ "id": 3, "controlPointId": 6, "value": "Yes" },
				{ "id": 4, "controlPointId": 6, "value": "No" }
			],
			"controlPointType": 1,
			"expectedValue": "Z-line",
			"units": "Yes/No",
			"toleranceText": "",
			"answer": ""
		},
		{
			"id": 7,
			"frequencyId": 1,
			"image": "https://syria.liveuamap.com/pics/2022/04/23/22430986_0.jpg",
			"type": 0,
			"lowerTolerance": null,
			"upperTolerance": null,
			"attributes": [{ "id": 109, "maxValue": null, "minValue": null }],
			"descriptions": "",
			"description": "This is a description",
			"frequency": [
				{
					"id": 1,
					"to25": 23,
					"to50": 2,
					"to100": 343,
					"to200": 5,
					"to300": 5,
					"to500": 6,
					"to700": 66,
					"to1000": 7,
					"to1500": 5,
					"to2000": 76,
					"to3000": 76,
					"to4000": 766,
					"to5000": 69
				}
			],
			"options": [
				{ "id": 5, "controlPointId": 7, "value": "Yes" },
				{ "id": 6, "controlPointId": 7, "value": "No" }
			],
			"controlPointType": 1,
			"expectedValue": "Fiber",
			"units": "Yes/No",
			"toleranceText": "",
			"answer": ""
		}
	],
	"oneTimeControlPoints": [
		{
			"id": 1,
			"frequencyId": 1,
			"image": "https://syria.liveuamap.com/pics/2022/04/23/22430986_0.jpg",
			"type": 3,
			"lowerTolerance": null,
			"upperTolerance": null,
			"attributes": [{ "id": 3, "maxValue": null, "minValue": null }],
			"descriptions": "",
			"description": "This is a description",
			"frequency": [
				{
					"id": 1,
					"to25": 23,
					"to50": 2,
					"to100": 343,
					"to200": 5,
					"to300": 5,
					"to500": 6,
					"to700": 66,
					"to1000": 7,
					"to1500": 5,
					"to2000": 76,
					"to3000": 76,
					"to4000": 766,
					"to5000": 69
				}
			],
			"controlPointType": 1,
			"expectedValue": "300.00",
			"units": "mm",
			"toleranceText": "",
			"answer": ""
		},
		{
			"id": 2,
			"frequencyId": 1,
			"image": "https://syria.liveuamap.com/pics/2022/04/23/22430986_0.jpg",
			"type": 3,
			"lowerTolerance": 1,
			"upperTolerance": 1,
			"attributes": [{ "id": 4, "maxValue": 400, "minValue": 300 }],
			"descriptions": "",
			"description": "This is a description",
			"frequency": [
				{
					"id": 1,
					"to25": 23,
					"to50": 2,
					"to100": 343,
					"to200": 5,
					"to300": 5,
					"to500": 6,
					"to700": 66,
					"to1000": 7,
					"to1500": 5,
					"to2000": 76,
					"to3000": 76,
					"to4000": 766,
					"to5000": 69
				}
			],
			"controlPointType": 1,
			"expectedValue": "390.00",
			"units": "mm",
			"toleranceText": "+/-1mm",
			"answer": ""
		},
		{
			"id": 3,
			"frequencyId": 1,
			"image": "https://syria.liveuamap.com/pics/2022/04/23/22430986_0.jpg",
			"type": 3,
			"lowerTolerance": 1,
			"upperTolerance": 6,
			"attributes": [{ "id": 49, "maxValue": 50, "minValue": 30 }],
			"descriptions": "",
			"description": "This is a description",
			"frequency": [
				{
					"id": 1,
					"to25": 23,
					"to50": 2,
					"to100": 343,
					"to200": 5,
					"to300": 5,
					"to500": 6,
					"to700": 66,
					"to1000": 7,
					"to1500": 5,
					"to2000": 76,
					"to3000": 76,
					"to4000": 766,
					"to5000": 69
				}
			],
			"controlPointType": 1,
			"expectedValue": "47",
			"units": "mm",
			"toleranceText": "+6/-1mm",
			"answer": ""
		},
		{
			"id": 4,
			"frequencyId": 1,
			"image": "https://syria.liveuamap.com/pics/2022/04/23/22430986_0.jpg",
			"type": 1,
			"lowerTolerance": null,
			"upperTolerance": null,
			"attributes": [{ "id": 51, "maxValue": null, "minValue": null }],
			"descriptions": "",
			"description": "This is a description",
			"frequency": [
				{
					"id": 1,
					"to25": 23,
					"to50": 2,
					"to100": 343,
					"to200": 5,
					"to300": 5,
					"to500": 6,
					"to700": 66,
					"to1000": 7,
					"to1500": 5,
					"to2000": 76,
					"to3000": 76,
					"to4000": 766,
					"to5000": 69
				}
			],
			"controlPointType": 1,
			"expectedValue": "ISO ePM10 50%",
			"units": "Text",
			"toleranceText": "",
			"answer": ""
		},
		{
			"id": 5,
			"frequencyId": 1,
			"image": "https://syria.liveuamap.com/pics/2022/04/23/22430986_0.jpg",
			"type": 0,
			"lowerTolerance": null,
			"upperTolerance": null,
			"attributes": [{ "id": 70, "maxValue": null, "minValue": null }],
			"descriptions": "",
			"description": "This is a description",
			"frequency": [
				{
					"id": 1,
					"to25": 23,
					"to50": 2,
					"to100": 343,
					"to200": 5,
					"to300": 5,
					"to500": 6,
					"to700": 66,
					"to1000": 7,
					"to1500": 5,
					"to2000": 76,
					"to3000": 76,
					"to4000": 766,
					"to5000": 69
				}
			],
			"options": [
				{ "id": 1, "controlPointId": 5, "value": "Yes" },
				{ "id": 2, "controlPointId": 5, "value": "No" }
			],
			"controlPointType": 1,
			"expectedValue": "Ja",
			"units": "Yes/No",
			"toleranceText": "",
			"answer": ""
		},
		{
			"id": 6,
			"frequencyId": 1,
			"image": "https://syria.liveuamap.com/pics/2022/04/23/22430986_0.jpg",
			"type": 0,
			"lowerTolerance": null,
			"upperTolerance": null,
			"attributes": [{ "id": 104, "maxValue": null, "minValue": null }],
			"descriptions": "",
			"description": "This is a description",
			"frequency": [
				{
					"id": 1,
					"to25": 23,
					"to50": 2,
					"to100": 343,
					"to200": 5,
					"to300": 5,
					"to500": 6,
					"to700": 66,
					"to1000": 7,
					"to1500": 5,
					"to2000": 76,
					"to3000": 76,
					"to4000": 766,
					"to5000": 69
				}
			],
			"options": [
				{ "id": 3, "controlPointId": 6, "value": "Yes" },
				{ "id": 4, "controlPointId": 6, "value": "No" }
			],
			"controlPointType": 1,
			"expectedValue": "Z-line",
			"units": "Yes/No",
			"toleranceText": "",
			"answer": ""
		},
		{
			"id": 7,
			"frequencyId": 1,
			"image": "https://syria.liveuamap.com/pics/2022/04/23/22430986_0.jpg",
			"type": 0,
			"lowerTolerance": null,
			"upperTolerance": null,
			"attributes": [{ "id": 109, "maxValue": null, "minValue": null }],
			"descriptions": "",
			"description": "This is a description",
			"frequency": [
				{
					"id": 1,
					"to25": 23,
					"to50": 2,
					"to100": 343,
					"to200": 5,
					"to300": 5,
					"to500": 6,
					"to700": 66,
					"to1000": 7,
					"to1500": 5,
					"to2000": 76,
					"to3000": 76,
					"to4000": 766,
					"to5000": 69
				}
			],
			"options": [
				{ "id": 5, "controlPointId": 7, "value": "Yes" },
				{ "id": 6, "controlPointId": 7, "value": "No" }
			],
			"controlPointType": 1,
			"expectedValue": "Fiber",
			"units": "Yes/No",
			"toleranceText": "",
			"answer": ""
		}
	],
	"multipleTimeControlPoints": [
		{
			"id": 1,
			"frequencyId": 1,
			"image": "https://syria.liveuamap.com/pics/2022/04/23/22430986_0.jpg",
			"type": 3,
			"lowerTolerance": null,
			"upperTolerance": null,
			"attributes": [{ "id": 3, "maxValue": null, "minValue": null }],
			"descriptions": "",
			"description": "This is a description",
			"frequency": [
				{
					"id": 1,
					"to25": 23,
					"to50": 2,
					"to100": 343,
					"to200": 5,
					"to300": 5,
					"to500": 6,
					"to700": 66,
					"to1000": 7,
					"to1500": 5,
					"to2000": 76,
					"to3000": 76,
					"to4000": 766,
					"to5000": 69
				}
			],
			"controlPointType": 1,
			"expectedValue": "300.00",
			"units": "mm",
			"toleranceText": "",
			"answer": "",
			"letter": "A"
		},
		{
			"id": 2,
			"frequencyId": 1,
			"image": "https://syria.liveuamap.com/pics/2022/04/23/22430986_0.jpg",
			"type": 3,
			"lowerTolerance": 1,
			"upperTolerance": 1,
			"attributes": [{ "id": 4, "maxValue": 400, "minValue": 300 }],
			"descriptions": "",
			"description": "This is a description",
			"frequency": [
				{
					"id": 1,
					"to25": 23,
					"to50": 2,
					"to100": 343,
					"to200": 5,
					"to300": 5,
					"to500": 6,
					"to700": 66,
					"to1000": 7,
					"to1500": 5,
					"to2000": 76,
					"to3000": 76,
					"to4000": 766,
					"to5000": 69
				}
			],
			"controlPointType": 1,
			"expectedValue": "390.00",
			"units": "mm",
			"toleranceText": "+/-1mm",
			"answer": "",
			"letter": "B"
		},
		{
			"id": 3,
			"frequencyId": 1,
			"image": "https://syria.liveuamap.com/pics/2022/04/23/22430986_0.jpg",
			"type": 3,
			"lowerTolerance": 1,
			"upperTolerance": 6,
			"attributes": [{ "id": 49, "maxValue": 50, "minValue": 30 }],
			"descriptions": "",
			"description": "This is a description",
			"frequency": [
				{
					"id": 1,
					"to25": 23,
					"to50": 2,
					"to100": 343,
					"to200": 5,
					"to300": 5,
					"to500": 6,
					"to700": 66,
					"to1000": 7,
					"to1500": 5,
					"to2000": 76,
					"to3000": 76,
					"to4000": 766,
					"to5000": 69
				}
			],
			"controlPointType": 1,
			"expectedValue": "47",
			"units": "mm",
			"toleranceText": "+6/-1mm",
			"answer": "",
			"letter": "C"
		},
		{
			"id": 4,
			"frequencyId": 1,
			"image": "https://syria.liveuamap.com/pics/2022/04/23/22430986_0.jpg",
			"type": 1,
			"lowerTolerance": null,
			"upperTolerance": null,
			"attributes": [{ "id": 51, "maxValue": null, "minValue": null }],
			"descriptions": "",
			"description": "This is a description",
			"frequency": [
				{
					"id": 1,
					"to25": 23,
					"to50": 2,
					"to100": 343,
					"to200": 5,
					"to300": 5,
					"to500": 6,
					"to700": 66,
					"to1000": 7,
					"to1500": 5,
					"to2000": 76,
					"to3000": 76,
					"to4000": 766,
					"to5000": 69
				}
			],
			"controlPointType": 1,
			"expectedValue": "ISO ePM10 50%",
			"units": "Text",
			"toleranceText": "",
			"answer": "",
			"letter": "D"
		},
		{
			"id": 5,
			"frequencyId": 1,
			"image": "https://syria.liveuamap.com/pics/2022/04/23/22430986_0.jpg",
			"type": 0,
			"lowerTolerance": null,
			"upperTolerance": null,
			"attributes": [{ "id": 70, "maxValue": null, "minValue": null }],
			"descriptions": "",
			"description": "This is a description",
			"frequency": [
				{
					"id": 1,
					"to25": 23,
					"to50": 2,
					"to100": 343,
					"to200": 5,
					"to300": 5,
					"to500": 6,
					"to700": 66,
					"to1000": 7,
					"to1500": 5,
					"to2000": 76,
					"to3000": 76,
					"to4000": 766,
					"to5000": 69
				}
			],
			"options": [
				{ "id": 1, "controlPointId": 5, "value": "Yes" },
				{ "id": 2, "controlPointId": 5, "value": "No" }
			],
			"controlPointType": 1,
			"expectedValue": "Ja",
			"units": "Yes/No",
			"toleranceText": "",
			"answer": "",
			"letter": "E"
		},
		{
			"id": 6,
			"frequencyId": 1,
			"image": "https://syria.liveuamap.com/pics/2022/04/23/22430986_0.jpg",
			"type": 0,
			"lowerTolerance": null,
			"upperTolerance": null,
			"attributes": [{ "id": 104, "maxValue": null, "minValue": null }],
			"descriptions": "",
			"description": "This is a description",
			"frequency": [
				{
					"id": 1,
					"to25": 23,
					"to50": 2,
					"to100": 343,
					"to200": 5,
					"to300": 5,
					"to500": 6,
					"to700": 66,
					"to1000": 7,
					"to1500": 5,
					"to2000": 76,
					"to3000": 76,
					"to4000": 766,
					"to5000": 69
				}
			],
			"options": [
				{ "id": 3, "controlPointId": 6, "value": "Yes" },
				{ "id": 4, "controlPointId": 6, "value": "No" }
			],
			"controlPointType": 1,
			"expectedValue": "Z-line",
			"units": "Yes/No",
			"toleranceText": "",
			"answer": "",
			"letter": "F"
		},
		{
			"id": 7,
			"frequencyId": 1,
			"image": "https://syria.liveuamap.com/pics/2022/04/23/22430986_0.jpg",
			"type": 0,
			"lowerTolerance": null,
			"upperTolerance": null,
			"attributes": [{ "id": 109, "maxValue": null, "minValue": null }],
			"descriptions": "",
			"description": "This is a description",
			"frequency": [
				{
					"id": 1,
					"to25": 23,
					"to50": 2,
					"to100": 343,
					"to200": 5,
					"to300": 5,
					"to500": 6,
					"to700": 66,
					"to1000": 7,
					"to1500": 5,
					"to2000": 76,
					"to3000": 76,
					"to4000": 766,
					"to5000": 69
				}
			],
			"options": [
				{ "id": 5, "controlPointId": 7, "value": "Yes" },
				{ "id": 6, "controlPointId": 7, "value": "No" }
			],
			"controlPointType": 1,
			"expectedValue": "Fiber",
			"units": "Yes/No",
			"toleranceText": "",
			"answer": "",
			"letter": "G"
		}
	],
	"multipleTimeAnswers": [
		[
			{ "id": 1, "answer": "", "type": 3 },
			{ "id": 1, "answer": "", "type": 3 },
			{ "id": 1, "answer": "", "type": 3 },
			{ "id": 1, "answer": "", "type": 3 },
			{ "id": 1, "answer": "", "type": 3 }
		],
		[
			{ "id": 2, "answer": "", "type": 3 },
			{ "id": 2, "answer": "", "type": 3 },
			{ "id": 2, "answer": "", "type": 3 },
			{ "id": 2, "answer": "", "type": 3 },
			{ "id": 2, "answer": "", "type": 3 }
		],
		[
			{ "id": 3, "answer": "", "type": 3 },
			{ "id": 3, "answer": "", "type": 3 },
			{ "id": 3, "answer": "", "type": 3 },
			{ "id": 3, "answer": "", "type": 3 },
			{ "id": 3, "answer": "", "type": 3 }
		],
		[
			{ "id": 4, "answer": "", "type": 1 },
			{ "id": 4, "answer": "", "type": 1 },
			{ "id": 4, "answer": "", "type": 1 },
			{ "id": 4, "answer": "", "type": 1 },
			{ "id": 4, "answer": "", "type": 1 }
		],
		[
			{ "id": 5, "answer": "", "type": 0 },
			{ "id": 5, "answer": "", "type": 0 },
			{ "id": 5, "answer": "", "type": 0 },
			{ "id": 5, "answer": "", "type": 0 },
			{ "id": 5, "answer": "", "type": 0 }
		],
		[
			{ "id": 6, "answer": "", "type": 0 },
			{ "id": 6, "answer": "", "type": 0 },
			{ "id": 6, "answer": "", "type": 0 },
			{ "id": 6, "answer": "", "type": 0 },
			{ "id": 6, "answer": "", "type": 0 }
		],
		[
			{ "id": 7, "answer": "", "type": 0 },
			{ "id": 7, "answer": "", "type": 0 },
			{ "id": 7, "answer": "", "type": 0 },
			{ "id": 7, "answer": "", "type": 0 },
			{ "id": 7, "answer": "", "type": 0 }
		]
	]
}


